Circles_RestAPI_recruitment/__init__.py
Circles_RestAPI_recruitment/scraper_REST_API.py
rest_api_vacancy_scraper_local-0.0.2.dist-info/METADATA
rest_api_vacancy_scraper_local-0.0.2.dist-info/WHEEL
rest_api_vacancy_scraper_local-0.0.2.dist-info/top_level.txt
rest_api_vacancy_scraper_local-0.0.2.dist-info/RECORD
