Metadata-Version: 2.1
Name: rest-api-vacancy-scraper-local
Version: 0.0.2
Summary: PyPI Package for Circles Local RestAPI recruitment Python
Home-page: https://github.com/javatechy/dokr
Author: Circles
Author-email: info@circles.life
Classifier: Programming Language :: Python :: 3
Classifier: License :: Other/Proprietary License
Classifier: Operating System :: OS Independent
